proteinynbn/__init__.py
proteinynbn/IRAP/__init__.py
proteinynbn/IRAP/irap.txt
proteinynbn/IRAP/utils.py
proteinynbn/basic_seq/__init__.py
proteinynbn/basic_seq/seqs.py
proteinynbn/model_modules/__init__.py
proteinynbn/model_modules/tokenizer.py
proteinynbn/tf_model_modules/InputModule.py
proteinynbn/tf_model_modules/PrintTfrecord.py
proteinynbn/tf_model_modules/__init__.py
proteinynbn/tf_model_modules/mask_fm_bert.py
proteinynbn-0.3.8.dist-info/licenses/LICENSE
test/__init__.py
proteinynbn-0.3.8.dist-info/METADATA
proteinynbn-0.3.8.dist-info/WHEEL
proteinynbn-0.3.8.dist-info/top_level.txt
proteinynbn-0.3.8.dist-info/RECORD
